gpt_term/__init__.py
gpt_term/__main__.py
gpt_term/_version.py
gpt_term/config.ini
gpt_term/locale.py
gpt_term/main.py
gpt_term/locale/gpt_term.de.yml
gpt_term/locale/gpt_term.en.yml
gpt_term/locale/gpt_term.jp.yml
gpt_term/locale/gpt_term.zh_CN.yml
gpt_term-1.3.1.dist-info/LICENSE
gpt_term-1.3.1.dist-info/METADATA
gpt_term-1.3.1.dist-info/WHEEL
gpt_term-1.3.1.dist-info/entry_points.txt
gpt_term-1.3.1.dist-info/top_level.txt
gpt_term-1.3.1.dist-info/RECORD
