Metadata-Version: 2.1
Name: gpt-term
Version: 1.3.1
Summary: Chat with GPT in Terminal
Author: xiaoxx970, Ace-Radom
License: MIT License
Project-URL: Homepage, https://github.com/xiaoxx970/chatgpt-in-terminal/
Classifier: Programming Language :: Python :: 3
Classifier: License :: OSI Approved :: MIT License
Classifier: Operating System :: OS Independent
Classifier: Environment :: Console
Requires-Python: >=3.7
License-File: LICENSE
Requires-Dist: requests
Requires-Dist: pyperclip
Requires-Dist: rich >=13.3.1
Requires-Dist: prompt-toolkit >=3.0
Requires-Dist: sseclient-py >=1.7.2
Requires-Dist: tiktoken
Requires-Dist: packaging
Requires-Dist: python-i18n
Requires-Dist: pyyaml
